Metadata-Version: 1.0
Name: fanc
Version: 0.9.20
Summary: Framework for the ANalysis of C-data.
Home-page: UNKNOWN
Author: UNKNOWN
Author-email: UNKNOWN
License: UNKNOWN
Platform: UNKNOWN
